Metadata-Version: 2.1
Name: SilverStreamingApplicationDQ
Version: 1.8
Summary: Improved appends logic to Bronze delta target
Home-page: UNKNOWN
Author: 
Author-email: 
License: UNKNOWN
Platform: UNKNOWN
